quat/__init__.py
quat/quat.py
quat-1.0.0.dist-info/METADATA
quat-1.0.0.dist-info/WHEEL
quat-1.0.0.dist-info/top_level.txt
quat-1.0.0.dist-info/RECORD
