Metadata-Version: 2.1
Name: quat
Version: 1.0.0
Summary: A simple library for working with quaternions and vectors.
Home-page: https://github.com/OmidAlek/quat
Author: Majid Alekasir
Author-email: <majid.alekasir@gmail.com>
Keywords: python,quaternion,vector,XYZVector,IMU,DMP
Classifier: Development Status :: 5 - Production/Stable
Classifier: Intended Audience :: Developers
Classifier: Programming Language :: Python :: 3.10
Classifier: Operating System :: Unix
Classifier: Operating System :: MacOS :: MacOS X
